navdeep/CODE1.py
navdeep/CODE2.py
navdeep/__init__.py
navdeep-0.0.7.dist-info/METADATA
navdeep-0.0.7.dist-info/WHEEL
navdeep-0.0.7.dist-info/top_level.txt
navdeep-0.0.7.dist-info/RECORD
