Metadata-Version: 2.1
Name: navdeep
Version: 0.0.7
Summary: lets you know if given int is prime or odd or even
Home-page: https://github.com/Navdeep6/tpackage
Author: Navdeep
Author-email: sujith133@gmail.com
License: UNKNOWN
Platform: UNKNOWN
Classifier: Programming Language :: Python :: 3
Classifier: License :: OSI Approved :: MIT License
Classifier: Operating System :: OS Independent
Requires-Python: >=3.6
